{
  "dir": "\u003ccli-dir\u003e/blacklane-pp-cli",
  "spec_path": "\u003ccli-dir\u003e/spec.yaml",
  "spec_source": "bundled",
  "verdict": "WARN",
  "path_check": {
    "tested": 0,
    "valid": 0,
    "valid_pct": 0,
    "skipped": true,
    "detail": "internal-yaml spec: paths validated at parse time"
  },
  "auth_check": {
    "spec_scheme": "",
    "generated_format": "unknown",
    "match": true,
    "detail": "no bot/bearer/basic scheme detected"
  },
  "browser_session_check": {
    "required": false,
    "pass": true,
    "detail": "browser-session auth not required"
  },
  "oauth_scope_coverage_check": {
    "checked": 0,
    "covered": 0,
    "skipped": true,
    "detail": "no OAuth-scoped endpoints in spec"
  },
  "dead_flags": {
    "total": 20,
    "dead": 0
  },
  "dead_functions": {
    "total": 65,
    "dead": 1,
    "items": [
      "partialFailureErr"
    ]
  },
  "pipeline_check": {
    "sync_calls_domain": true,
    "search_calls_domain": false,
    "domain_tables": 1,
    "sync_file_emitted": true,
    "sync_resources_present": false,
    "detail": "sync uses domain-specific Upsert methods; search methods not found; 1 domain tables found; defaultSyncResources empty (sync command is a no-op)"
  },
  "example_check": {
    "tested": 10,
    "with_examples": 10,
    "valid_examples": 10,
    "detail": "10/10 commands have examples"
  },
  "wiring_check": {
    "command_tree": {
      "defined": 37,
      "registered": 37
    },
    "config_consistency": {
      "consistent": true
    },
    "workflow_completeness": {
      "skipped": true,
      "total_steps": 0,
      "mapped_steps": 0,
      "detail": "no workflow_verify.yaml found"
    }
  },
  "novel_features_check": {
    "planned": 9,
    "found": 9
  },
  "mcp_surface_parity": {
    "state": "runtime_walking",
    "pass": true,
    "detail": "MCP surface mirrors the Cobra tree at runtime"
  },
  "reimplementation_check": {
    "checked": 9,
    "exempted_via_store": 2,
    "missing_data_source_strategy": [
      {
        "command": "watch",
        "file": "ledger.go",
        "reason": "missing // pp:data-source \u003cauto|local|live\u003e annotation"
      },
      {
        "command": "compare",
        "file": "quote.go",
        "reason": "missing // pp:data-source \u003cauto|local|live\u003e annotation"
      },
      {
        "command": "trip",
        "file": "quote.go",
        "reason": "missing // pp:data-source \u003cauto|local|live\u003e annotation"
      },
      {
        "command": "fit",
        "file": "quote.go",
        "reason": "missing // pp:data-source \u003cauto|local|live\u003e annotation"
      },
      {
        "command": "log",
        "file": "ledger.go",
        "reason": "missing // pp:data-source \u003cauto|local|live\u003e annotation"
      },
      {
        "command": "bookings",
        "file": "account.go",
        "reason": "missing // pp:data-source \u003cauto|local|live\u003e annotation"
      },
      {
        "command": "me",
        "file": "account.go",
        "reason": "missing // pp:data-source \u003cauto|local|live\u003e annotation"
      },
      {
        "command": "wallet",
        "file": "account.go",
        "reason": "missing // pp:data-source \u003cauto|local|live\u003e annotation"
      },
      {
        "command": "book",
        "file": "book.go",
        "reason": "missing // pp:data-source \u003cauto|local|live\u003e annotation"
      }
    ]
  },
  "source_client_check": {
    "checked": 0,
    "skipped": true
  },
  "print_json_filtered_check": {
    "checked": 25
  },
  "test_presence": {
    "checked": 0
  },
  "naming_check": {
    "checked": 25
  },
  "sync_param_drop_check": {
    "checked": 0,
    "skipped": true
  },
  "issues": [
    "1 dead helper functions found",
    "defaultSyncResources empty: sync command is a runtime no-op; store-dependent novel commands have no advertised population path"
  ]
}